{
  "_type": "export",
  "__export_format": 4,
  "__export_date": "2024-10-23T09:21:00.000Z",
  "__export_source": "insomnia.desktop.app:v2023.5.8",
  "resources": [
    {
      "_id": "wrk_001",
      "_type": "workspace",
      "name": "Sistema de Controle de Estoque - API",
      "description": "API completa para gestão de estoque de ferramentas em português brasileiro"
    },
    {
      "_id": "env_base",
      "_type": "environment",
      "name": "Base Environment",
      "data": {
        "base_url": "http://localhost:5001"
      }
    },
    {
      "_id": "req_health",
      "_type": "request",
      "parentId": "wrk_001",
      "name": "Health Check",
      "url": "{{ base_url }}/health",
      "method": "GET",
      "description": "Verificar saúde da API e conexão com banco de dados"
    },
    {
      "_id": "fld_users",
      "_type": "request_group",
      "parentId": "wrk_001",
      "name": "Usuários",
      "description": "Gestão de usuários do sistema"
    },
    {
      "_id": "req_user_login",
      "_type": "request",
      "parentId": "fld_users",
      "name": "Login",
      "url": "{{ base_url }}/users/login",
      "method": "POST",
      "body": {
        "mimeType": "application/json",
        "text": "{\n  \"email\": \"admin@ferramentas.com\",\n  \"password\": \"admin123\"\n}"
      },
      "description": "Autenticar usuário no sistema"
    },
    {
      "_id": "req_user_create",
      "_type": "request",
      "parentId": "fld_users",
      "name": "Criar Usuário",
      "url": "{{ base_url }}/users/create",
      "method": "POST",
      "body": {
        "mimeType": "application/json",
        "text": "{\n  \"name\": \"Carlos Silva\",\n  \"email\": \"carlos.silva@ferramentas.com\",\n  \"password\": \"password123\",\n  \"gender_id\": \"550e8400-e29b-41d4-a716-446655440001\",\n  \"role_id\": \"660e8400-e29b-41d4-a716-446655440003\"\n}"
      },
      "description": "Criar novo usuário no sistema"
    },
    {
      "_id": "req_user_read_all",
      "_type": "request",
      "parentId": "fld_users",
      "name": "Listar Todos Usuários",
      "url": "{{ base_url }}/users/read/all",
      "method": "GET",
      "description": "Listar todos os usuários ativos"
    },
    {
      "_id": "req_user_me",
      "_type": "request",
      "parentId": "fld_users",
      "name": "Meu Perfil",
      "url": "{{ base_url }}/users/me",
      "method": "GET",
      "description": "Obter perfil do usuário atual"
    },
    {
      "_id": "req_change_password",
      "_type": "request",
      "parentId": "fld_users",
      "name": "Alterar Senha",
      "url": "{{ base_url }}/users/change-password",
      "method": "POST",
      "body": {
        "mimeType": "application/json",
        "text": "{\n  \"current_password\": \"senha_antiga\",\n  \"new_password\": \"nova_senha123\"\n}"
      },
      "description": "Alterar senha do usuário"
    },
    {
      "_id": "fld_products",
      "_type": "request_group",
      "parentId": "wrk_001",
      "name": "Produtos",
      "description": "Gestão de produtos do estoque"
    },
    {
      "_id": "req_product_create",
      "_type": "request",
      "parentId": "fld_products",
      "name": "Criar Produto",
      "url": "{{ base_url }}/products/create",
      "method": "POST",
      "body": {
        "mimeType": "application/json",
        "text": "{\n  \"name\": \"Martelo de Carpinteiro 500g\",\n  \"category_id\": \"770e8400-e29b-41d4-a716-446655440001\",\n  \"warehouse_id\": \"880e8400-e29b-41d4-a716-446655440001\",\n  \"min_quantity\": 25.00,\n  \"unit_cost\": 45.90,\n  \"observation\": \"Martelo profissional com cabo de fibra\"\n}"
      },
      "description": "Criar novo produto no estoque"
    },
    {
      "_id": "req_product_read_all",
      "_type": "request",
      "parentId": "fld_products",
      "name": "Listar Todos Produtos",
      "url": "{{ base_url }}/products/read/all",
      "method": "GET",
      "description": "Listar todos os produtos ativos"
    },
    {
      "_id": "req_product_low_stock",
      "_type": "request",
      "parentId": "fld_products",
      "name": "Produtos com Estoque Baixo",
      "url": "{{ base_url }}/products/read/low-stock",
      "method": "GET",
      "description": "Listar produtos com estoque abaixo do mínimo"
    },
    {
      "_id": "req_product_by_category",
      "_type": "request",
      "parentId": "fld_products",
      "name": "Produtos por Categoria",
      "url": "{{ base_url }}/products/read/category/770e8400-e29b-41d4-a716-446655440001",
      "method": "GET",
      "description": "Listar produtos por categoria específica"
    },
    {
      "_id": "req_product_by_warehouse",
      "_type": "request",
      "parentId": "fld_products",
      "name": "Produtos por Armazém",
      "url": "{{ base_url }}/products/read/warehouse/880e8400-e29b-41d4-a716-446655440001",
      "method": "GET",
      "description": "Listar produtos por armazém específico"
    },
    {
      "_id": "fld_categories",
      "_type": "request_group",
      "parentId": "wrk_001",
      "name": "Categorias",
      "description": "Gestão de categorias de produtos"
    },
    {
      "_id": "req_category_create",
      "_type": "request",
      "parentId": "fld_categories",
      "name": "Criar Categoria",
      "url": "{{ base_url }}/categories/create",
      "method": "POST",
      "body": {
        "mimeType": "application/json",
        "text": "{\n  \"name\": \"Ferramentas de Jardinagem\",\n  \"description\": \"Machados, podadoras e ferramentas de jardinagem\"\n}"
      },
      "description": "Criar nova categoria de produtos"
    },
    {
      "_id": "req_category_read_all",
      "_type": "request",
      "parentId": "fld_categories",
      "name": "Listar Todas Categorias",
      "url": "{{ base_url }}/categories/read/all",
      "method": "GET",
      "description": "Listar todas as categorias ativas"
    },
    {
      "_id": "fld_warehouses",
      "_type": "request_group",
      "parentId": "wrk_001",
      "name": "Armazéns",
      "description": "Gestão de armazéns e depósitos"
    },
    {
      "_id": "req_warehouse_create",
      "_type": "request",
      "parentId": "fld_warehouses",
      "name": "Criar Armazém",
      "url": "{{ base_url }}/warehouses/create",
      "method": "POST",
      "body": {
        "mimeType": "application/json",
        "text": "{\n  \"name\": \"Brasília - Centro-Oeste\",\n  \"description\": \"Armazém regional no Distrito Federal\"\n}"
      },
      "description": "Criar novo armazém/deposito"
    },
    {
      "_id": "req_warehouse_read_all",
      "_type": "request",
      "parentId": "fld_warehouses",
      "name": "Listar Todos Armazéns",
      "url": "{{ base_url }}/warehouses/read/all",
      "method": "GET",
      "description": "Listar todos os armazéns ativos"
    },
    {
      "_id": "fld_entries",
      "_type": "request_group",
      "parentId": "wrk_001",
      "name": "Entradas de Estoque",
      "description": "Gestão de entradas de produtos no estoque"
    },
    {
      "_id": "req_entry_create",
      "_type": "request",
      "parentId": "fld_entries",
      "name": "Registrar Entrada",
      "url": "{{ base_url }}/entries/create",
      "method": "POST",
      "body": {
        "mimeType": "application/json",
        "text": "{\n  \"product_id\": \"aa0e8400-e29b-41d4-a716-446655440001\",\n  \"entry_date\": \"2024-01-25\",\n  \"quantity\": 100.00,\n  \"observation\": \"Compra em quantidade - fornecedor nacional\"\n}"
      },
      "description": "Registrar nova entrada de estoque"
    },
    {
      "_id": "req_entry_read_all",
      "_type": "request",
      "parentId": "fld_entries",
      "name": "Listar Todas Entradas",
      "url": "{{ base_url }}/entries/read/all",
      "method": "GET",
      "description": "Listar todas as entradas de estoque"
    },
    {
      "_id": "req_entry_by_date_range",
      "_type": "request",
      "parentId": "fld_entries",
      "name": "Entradas por Período",
      "url": "{{ base_url }}/entries/read/date-range",
      "method": "POST",
      "body": {
        "mimeType": "application/json",
        "text": "{\n  \"start_date\": \"2024-01-01\",\n  \"end_date\": \"2024-01-31\"\n}"
      },
      "description": "Listar entradas por período específico"
    },
    {
      "_id": "fld_exits",
      "_type": "request_group",
      "parentId": "wrk_001",
      "name": "Saídas de Estoque",
      "description": "Gestão de saídas de produtos do estoque"
    },
    {
      "_id": "req_exit_create",
      "_type": "request",
      "parentId": "fld_exits",
      "name": "Registrar Saída",
      "url": "{{ base_url }}/exits/create",
      "method": "POST",
      "body": {
        "mimeType": "application/json",
        "text": "{\n  \"product_id\": \"aa0e8400-e29b-41d4-a716-446655440001\",\n  \"exit_date\": \"2024-01-20\",\n  \"quantity\": 5.00,\n  \"observation\": \"Distribuição para equipe de manutenção\"\n}"
      },
      "description": "Registrar nova saída de estoque"
    },
    {
      "_id": "req_exit_read_all",
      "_type": "request",
      "parentId": "fld_exits",
      "name": "Listar Todas Saídas",
      "url": "{{ base_url }}/exits/read/all",
      "method": "GET",
      "description": "Listar todas as saídas de estoque"
    },
    {
      "_id": "req_exit_by_date_range",
      "_type": "request",
      "parentId": "fld_exits",
      "name": "Saídas por Período",
      "url": "{{ base_url }}/exits/read/date-range",
      "method": "POST",
      "body": {
        "mimeType": "application/json",
        "text": "{\n  \"start_date\": \"2024-02-01\",\n  \"end_date\": \"2024-02-29\"\n}"
      },
      "description": "Listar saídas por período específico"
    },
    {
      "_id": "fld_reference",
      "_type": "request_group",
      "parentId": "wrk_001",
      "name": "Dados de Referência",
      "description": "Dados auxiliares do sistema"
    },
    {
      "_id": "req_genders_read_all",
      "_type": "request",
      "parentId": "fld_reference",
      "name": "Listar Gêneros",
      "url": "{{ base_url }}/gender/read/all",
      "method": "GET",
      "description": "Listar todos os gêneros cadastrados"
    },
    {
      "_id": "req_roles_read_all",
      "_type": "request",
      "parentId": "fld_reference",
      "name": "Listar Cargos",
      "url": "{{ base_url }}/roles/read/all",
      "method": "GET",
      "description": "Listar todos os cargos/perfis do sistema"
    }
  ]
}